.travis.yml
AUTHORS
ChangeLog
LICENSE
README.rst
requirements.txt
setup.cfg
setup.py
test-requirements.txt
tox.ini
doc/Makefile
doc/conf.py
doc/index.rst
doc/make.bat
jenkins_job_builder_naginator.egg-info/PKG-INFO
jenkins_job_builder_naginator.egg-info/SOURCES.txt
jenkins_job_builder_naginator.egg-info/dependency_links.txt
jenkins_job_builder_naginator.egg-info/entry_points.txt
jenkins_job_builder_naginator.egg-info/not-zip-safe
jenkins_job_builder_naginator.egg-info/requires.txt
jenkins_job_builder_naginator.egg-info/top_level.txt
naginator_publisher/__init__.py
test/__init__.py
test/base.py
test/test_naginator.py
test/fixtures/naginator_default.xml
test/fixtures/naginator_default.yaml
test/fixtures/naginator_fixed.xml
test/fixtures/naginator_fixed.yaml
test/fixtures/naginator_progressive.xml
test/fixtures/naginator_progressive.yaml
test/fixtures/naginator_regexp.xml
test/fixtures/naginator_regexp.yaml
tools/release.bash