Metadata-Version: 1.0
Name: jenkins-job-builder-naginator
Version: 0.0.1
Summary: Automatically reschedule a build after a build failure.
Home-page: https://github.com/thomasvandoren/jenkins-job-builder-naginator
Author: Thomas Van Doren
Author-email: thomas.vandoren@gmail.com
License: Apache License, Version 2.0
Platform: UNKNOWN
